pupil.py
pypupil/__init__.py
pypupil/affine_transformer.py
pypupil/pupil.py
pypupil/pupil_test.py
pypupil/pypupil_main.py
pypupil/serializer.py
pypupil/synchonizer.py
pypupil-0.1.9.dist-info/LICENSE
pypupil-0.1.9.dist-info/METADATA
pypupil-0.1.9.dist-info/WHEEL
pypupil-0.1.9.dist-info/top_level.txt
pypupil-0.1.9.dist-info/RECORD
