Metadata-Version: 2.1
Name: pypupil
Version: 0.1.9
Summary: Eye tracker (Pupil-labs) helper in Python3
Home-page: https://github.com/choisuyeon/pypupil
Author: Suyeon Choi
Author-email: suyn.choi@gmail.com
License: UNKNOWN
Platform: UNKNOWN
Classifier: Programming Language :: Python :: 3
Classifier: License :: OSI Approved :: MIT License
Classifier: Operating System :: OS Independent
